{
    "airpillow": {
        "name": "airpillow", 
        "tags": ["swimming"],
        "weather": ["sunny"],
        "url": "images/objects/airpillow.png"
    },
    "blanket": {
        "name": "blanket", 
        "tags": ["business"],
        "weather": [],
        "url": "images/objects/blanket.png"
    },
    "flashlight": {
        "name": "flashlight", 
        "tags": ["skiing"],
        "weather": ["snow"],
        "url": "images/objects/flashlight.png"
    },
    "lighter": {
        "name": "lighter", 
        "tags": ["skiing"],
        "weather": ["snow"],
        "url": "images/objects/lighter.png"
    },
    "raincoat": {
        "name": "raincoat", 
        "tags": ["skiing", "business"],
        "weather": [],
        "url": "images/objects/raincoat.png"
    },
    "utensils": {
        "name": "utensils", 
        "tags": ["business"],
        "weather": [],
        "url": "images/objects/utensils.png"
    }

}